<sequencer_type id="454_life_sciences" name="454 Life Sciences" version="1.0.0">
    <description></description>
    <version>1</version>
 
    <data_transfer_settings>
        <data_transfer protocol='scp' automatic_transfer='False' host='host' user_name='user_name' password='password' data_location='data_location' />
    </data_transfer_settings>
 
    <run_details>
        <results>
            <dataset name="dataset1_name" datatype="dataset1_datatype" />
        </results>
    </run_details>
 
    <form type="external_service" name="Applied Biosystems SOLiD Form" description="">
        <fields>
            <field name="host" type="text" label="Hostname or IP address" description="" value="" required="True" />
            <field name="user_name" type="text" label="User name" description="User name to log into the sequencer." value="" required="True" />
            <field name="password" type="password" label="Password" description="" value="" required="True" />
            <field name="data_location" type="text" label="Data directory" description="" value="" required="False" />
            <field name="dataset1_name" type="text" label="Sample run output 1" description="" value="SFF file" required="True" />
            <field name="dataset1_datatype" type="text" label="Sample run datatype 1" description="" value="sff" required="True" />
        </fields>
    </form>

</sequencer_type>
